hoser/__init__.py
hoser/compile.py
hoser/run.py
hoser/serialize.py
hoser/streamutils.py
hoser/stdlib/__init__.py
hoser/stdlib/xargs.py
hoser-0.0.5.dist-info/LICENSE
hoser-0.0.5.dist-info/METADATA
hoser-0.0.5.dist-info/WHEEL
hoser-0.0.5.dist-info/top_level.txt
hoser-0.0.5.dist-info/RECORD
