Metadata-Version: 2.1
Name: hoser
Version: 0.0.5
Summary: Build data pipelines fast
Home-page: https://github.com/hoser-io/hoser-py
Author: Mark Asp
Author-email: masp <masp@github.com>
Project-URL: Homepage, https://github.com/hoser-io/hoser-py
Project-URL: Bug Tracker, https://github.com/hoser-io/hoser-py/issues
Classifier: Programming Language :: Python :: 3
Classifier: License :: OSI Approved :: MIT License
Classifier: Operating System :: OS Independent
Requires-Python: >=3.7
License-File: LICENSE
Requires-Dist: dill
Requires-Dist: typing-extensions
